{
  "slug": "lofi-space-vs-renaissance-reverb",
  "title": "Renaissance Reverb vs Lofi Space",
  "metaDescription": "Compare Renaissance Reverb by Waves with Lofi Space by Waves. See pricing, features, formats, and which reverb plugin is right for you.",
  "pluginA": {
    "id": "jx74wagsfv9d7b3pz48d7eg25s80hpdk",
    "name": "Renaissance Reverb",
    "slug": "renaissance-reverb",
    "manufacturer": "Waves",
    "manufacturerSlug": "waves",
    "description": "Smooth algorithmic reverb, 12 reverb types, 265 presets",
    "price": "$40",
    "priceRaw": 3999,
    "isFree": false,
    "category": "reverb",
    "formats": [
      "VST3",
      "AU",
      "AAX"
    ],
    "platforms": [
      "windows",
      "mac"
    ],
    "tags": [],
    "imageUrl": "https://media.wavescdn.com/images/products/plugins/600/renaissance-reverb.png?auto=format&ixlib=react-9.10.0&h=150",
    "productUrl": "https://www.waves.com/plugins/renaissance-reverb",
    "trendingScore": 0,
    "mentions7d": 0
  },
  "pluginB": {
    "id": "jx770y73q7jf940z7mbenf2q2580hab7",
    "name": "Lofi Space",
    "slug": "lofi-space",
    "manufacturer": "Waves",
    "manufacturerSlug": "waves",
    "description": "Lofi-style reverb and delay plugin",
    "price": "$35",
    "priceRaw": 3499,
    "isFree": false,
    "category": "reverb",
    "formats": [
      "VST3",
      "AU",
      "AAX"
    ],
    "platforms": [
      "windows",
      "mac"
    ],
    "tags": [],
    "imageUrl": "https://media.wavescdn.com/images/products/plugins/600/lofi-space.png?auto=format&ixlib=react-9.10.0&h=150",
    "productUrl": "https://www.waves.com/plugins/lofi-space",
    "trendingScore": 125,
    "mentions7d": 11
  },
  "comparison": {
    "category": "reverb",
    "priceWinner": "b",
    "trendingWinner": "b",
    "formatsA": "VST3, AU, AAX",
    "formatsB": "VST3, AU, AAX",
    "platformsA": "windows, mac",
    "platformsB": "windows, mac"
  },
  "generatedAt": 1770258289518
}